fileup.py
fileup-2.0.0.dist-info/LICENSE
fileup-2.0.0.dist-info/METADATA
fileup-2.0.0.dist-info/WHEEL
fileup-2.0.0.dist-info/entry_points.txt
fileup-2.0.0.dist-info/top_level.txt
fileup-2.0.0.dist-info/RECORD
